[
  {
    "id": "soul-seat",
    "name": "The Soul Seat",
    "brand": "Ikaria Design Co.",
    "category": "desk-chair",
    "price": "$1,278+",
    "priceNote": "Sold direct; no affiliate program — linked for reference.",
    "affiliateUrl": "https://www.ikariadesign.com/the-soul-seat",
    "retailer": "Ikaria Design",
    "tier": "premium",
    "rating": 4.6,
    "pros": [
      "A wide two-level perch that genuinely lets you sit cross-legged, kneel, or squat at a normal desk",
      "Backless and armless, so it invites constant position changes",
      "Handmade, height-adjustable, 90-day return"
    ],
    "cons": [
      "Expensive, and sold direct-only",
      "No back support — a feature, but an adjustment",
      "You may need to raise your desk 2–4″ to clear tucked knees"
    ],
    "bestFor": "The person who loved the idea in the intro: cross-legged at a standard desk, all day.",
    "verdict": "The category-defining piece. If floor-level work is the whole point, this is the one to covet.",
    "featured": true
  },
  {
    "id": "pipersong",
    "name": "Pipersong Meditation Chair",
    "brand": "Pipersong",
    "category": "desk-chair",
    "price": "$279–$439",
    "affiliateUrl": "https://pipersong.com/products/pipersong-pro",
    "retailer": "Pipersong / Amazon",
    "tier": "mid",
    "rating": 4.3,
    "pros": [
      "Cross-legged, kneeling, or conventional sitting with a movable footstool",
      "Has a height-adjustable back/side support the Soul Seat lacks",
      "A quarter of the price of the Soul Seat"
    ],
    "cons": [
      "Narrower seat than the Soul Seat's large platform",
      "More consumer-grade build; footstool can feel fiddly"
    ],
    "bestFor": "Fidgety desk workers who want position freedom without four figures.",
    "verdict": "The value pick in the cross-legged-desk niche, and the one with a real back option.",
    "featured": true
  },
  {
    "id": "vivo-cross-legged",
    "name": "VIVO Cross-Legged Chair",
    "brand": "VIVO",
    "category": "desk-chair",
    "price": "$99–$180",
    "affiliateUrl": "https://vivo-us.com/products/chair-cl02b",
    "retailer": "VIVO / Amazon",
    "tier": "budget",
    "rating": 3.8,
    "pros": [
      "Cheapest way to try cross-legged sitting at a desk",
      "Swivel seat, casters, adjustable height, a leg-rest extension"
    ],
    "cons": [
      "Basic padding and build",
      "Seat is narrower than the dedicated chairs — best for an ankle-over-knee tuck"
    ],
    "bestFor": "Testing the whole idea before committing to a Soul Seat or Pipersong.",
    "verdict": "A low-risk on-ramp. Fine to start; you may outgrow it.",
    "featured": false
  },
  {
    "id": "bean-zafu-zabuton",
    "name": "Zafu & Zabuton Cushion Set",
    "brand": "Bean Products",
    "category": "seating",
    "price": "$149.95",
    "affiliateUrl": "https://beanproducts.com/products/zafu-zabuton-meditation-cushion-set-cotton",
    "retailer": "Bean Products",
    "tier": "mid",
    "rating": 4.7,
    "pros": [
      "Buckwheat zafu you can adjust for height; hand-tufted cotton zabuton cushions the knees",
      "Removable, washable covers; made in the USA",
      "The floor-sitting starter kit in one box"
    ],
    "cons": [
      "Heavier than a bare cushion",
      "Buckwheat is firm — a love-it-or-not feel"
    ],
    "bestFor": "Anyone starting out: a firm seat to raise the hips plus a mat to save the knees and ankles.",
    "verdict": "The single best first purchase for making the floor inviting.",
    "featured": true
  },
  {
    "id": "bluecony-ikuko",
    "name": "IKUKO Seiza Bench",
    "brand": "Bluecony",
    "category": "seating",
    "price": "$169.95",
    "affiliateUrl": "https://www.bluecony.com/products/original",
    "retailer": "Bluecony",
    "tier": "premium",
    "rating": 4.5,
    "pros": [
      "Handmade solid birch with a curved seat — no cushion needed",
      "Detachable legs (no hinge to loosen), three heights sized to you",
      "Makes kneeling comfortable for far longer"
    ],
    "cons": [
      "Priciest bench in the category",
      "Slower to set up than a folding hinge"
    ],
    "bestFor": "People who love kneeling (seiza) but can't take the ankle and knee load unaided.",
    "verdict": "The reference seiza bench. Buy once.",
    "featured": false
  },
  {
    "id": "backjack",
    "name": "BackJack Floor Chair",
    "brand": "BackJack",
    "category": "seating",
    "price": "$58–$81",
    "affiliateUrl": "https://www.floorseating.com/",
    "retailer": "BackJack / Amazon",
    "tier": "budget",
    "rating": 4.2,
    "pros": [
      "A rigid steel frame gives real lumbar support at floor level",
      "Folds and stacks; a 20-year zendo and classroom staple"
    ],
    "cons": [
      "Only 2″ of foam — pair it with a cushion for long sits",
      "The upright back can encourage staying put rather than moving"
    ],
    "bestFor": "The biggest barrier to floor living for most Westerners: a tired lower back.",
    "verdict": "The honest fix for back fatigue. Cheap knock-offs collapse — get the real frame.",
    "featured": false
  },
  {
    "id": "nnewvante-floor-desk",
    "name": "Bamboo Floor Desk",
    "brand": "Nnewvante",
    "category": "desk",
    "price": "$50–$75",
    "affiliateUrl": "https://www.amazon.com/NNEWVANTE-Foldable-Adjustable-Breakfast-25-6x17-7in/dp/B0749JJ39S",
    "retailer": "Amazon",
    "tier": "budget",
    "rating": 4.3,
    "pros": [
      "Height-adjustable legs (~11–15″) that actually reach floor height",
      "Folds flat for storage; light, moisture-resistant bamboo"
    ],
    "cons": [
      "Best paired with a floor chair for back support",
      "Small top — fine for a laptop, tight with a mouse"
    ],
    "bestFor": "A true floor desk for working, eating, or writing at ground level.",
    "verdict": "The best-value entry into actual floor work. Not to be confused with a 'low' standing desk.",
    "featured": false
  },
  {
    "id": "fuli-shikibuton",
    "name": "Traditional Shiki Futon",
    "brand": "FULI",
    "category": "sleeping",
    "price": "~$299",
    "affiliateUrl": "https://fulijapan.com/products/futon-mattresses-shikibuton",
    "retailer": "FULI / Amazon",
    "tier": "mid",
    "rating": 4.2,
    "pros": [
      "A thin, roll-up cotton mattress — reclaim the room by day",
      "Made in Japan; medium-firm; rolls and folds easily"
    ],
    "cons": [
      "Side sleepers on a hard floor want a thicker layer",
      "Must be aired regularly or it can trap moisture"
    ],
    "bestFor": "Floor sleeping done properly, and small rooms that need to be many rooms.",
    "verdict": "Authentic and space-reclaiming — the antidote to a bed frame. Air it; don't leave it flat 24/7.",
    "featured": false
  },
  {
    "id": "emoor-tatami",
    "name": "Foldable Igusa Tatami Mat",
    "brand": "EMOOR",
    "category": "flooring",
    "price": "$70–$130",
    "affiliateUrl": "https://www.amazon.com/EMOOR-Japanese-Mattress-39x79in-Foldable/dp/B0876MZWVJ",
    "retailer": "Amazon",
    "tier": "mid",
    "rating": 4.1,
    "pros": [
      "Natural rush-grass surface — firm, breathable, and it smells wonderful",
      "Foldable and portable; a warm, honest base underfoot"
    ],
    "cons": [
      "Straw absorbs moisture — needs airing in humid homes",
      "Not for a damp basement slab without a vapour barrier"
    ],
    "bestFor": "A firm, insulating island of floor to sit, stretch, and nap on.",
    "verdict": "The most direct taste of a tatami room without a full remodel.",
    "featured": false
  },
  {
    "id": "strongtek-slant",
    "name": "Adjustable Slant Board",
    "brand": "StrongTek",
    "category": "props",
    "price": "$59.95",
    "affiliateUrl": "https://www.strong-tek.com/products/wooden-slant-board",
    "retailer": "StrongTek / Amazon",
    "tier": "budget",
    "rating": 4.6,
    "pros": [
      "Five angles to raise the heels and unlock a deep squat",
      "Sturdy hardwood, 450 lb capacity, doubles as a calf stretcher"
    ],
    "cons": [
      "A stack of books works too, for free",
      "One more thing to store"
    ],
    "bestFor": "Building the ankle range that makes getting down to (and up from) the floor easy.",
    "verdict": "The quiet MVP. Better squats mean more time on the floor with less complaint.",
    "featured": false
  },
  {
    "id": "lacrosse-balls",
    "name": "Lacrosse Balls (set)",
    "brand": "Rogue",
    "category": "mobility",
    "price": "$5–$12",
    "priceNote": "A tennis ball you already own is the free, softer starter.",
    "affiliateUrl": "https://www.roguefitness.com/rogue-lacrosse-balls",
    "retailer": "Rogue / any sporting goods store",
    "tier": "budget",
    "rating": 4.8,
    "pros": [
      "Feet, glutes, and upper back — the three desk-worker hot spots — for pocket change",
      "Firm enough to actually reach deep hip rotators where a foam roller can't",
      "Fits in a laptop bag; works against any wall or floor"
    ],
    "cons": [
      "The relief is neurological and temporary — a door-opener for movement, not a repair",
      "Easy to overdo; tender the next day if you grind instead of breathe"
    ],
    "bestFor": "The first dollar anyone should spend on mobility. Start with the soles of your feet.",
    "verdict": "The cheapest useful object in fitness. Buy two and lose one under the couch.",
    "featured": false
  },
  {
    "id": "yes4all-kettlebell",
    "name": "Powder-Coated Kettlebell",
    "brand": "Yes4All",
    "category": "mobility",
    "price": "$30–$60",
    "priceNote": "Buy by the kilo: 8 kg to learn the drills, 12–16 kg to grow into.",
    "affiliateUrl": "https://www.walmart.com/ip/Yes4All-8kg-18lb-Powder-Coated-Kettlebell-Single/287969962",
    "retailer": "Walmart / Amazon",
    "tier": "budget",
    "rating": 4.7,
    "pros": [
      "One bell covers halos, prying squats, arm bars, windmills, and get-ups for months",
      "Powder coat grips well without chalk; flat base won't roll away",
      "Probably the best cost-per-decade in home fitness"
    ],
    "cons": [
      "The swing and the get-up have a real learning curve — learn both unloaded first",
      "Cast iron and a bare floor need a mat between them"
    ],
    "bestFor": "Desk workers whose hips and shoulders are the rusty parts.",
    "verdict": "The single best ~$50 in home fitness. Start lighter than your ego suggests.",
    "featured": false
  },
  {
    "id": "whitin-barefoot",
    "name": "Barefoot Sneaker (wide toe box)",
    "brand": "Whitin",
    "category": "mobility",
    "price": "$40–$50",
    "priceNote": "Sold via Amazon; the budget way to test whether barefoot shoes suit you.",
    "affiliateUrl": "https://whitinshoes.com",
    "retailer": "Whitin / Amazon",
    "tier": "budget",
    "rating": 4.3,
    "pros": [
      "Wide toe box and zero drop at a third of the big-brand price",
      "Roomy enough for toes to actually splay",
      "Low-stakes entry: if barefoot isn't for you, you're out $45, not $160"
    ],
    "cons": [
      "Durability and refinement lag the premium brands",
      "Transition slowly regardless of price — your feet don't know what the shoes cost"
    ],
    "bestFor": "Trying the wide-toe-box life without a premium-brand commitment.",
    "verdict": "The gateway shoe. If your feet wake up happy after a month, upgrade later.",
    "featured": false
  },
  {
    "id": "xero-prio",
    "name": "Prio Barefoot Shoe",
    "brand": "Xero Shoes",
    "category": "mobility",
    "price": "$90–$110",
    "priceNote": "Sold direct and via Amazon; no affiliate relationship — linked for reference.",
    "affiliateUrl": "https://xeroshoes.com/shop/shoes/prio-men/",
    "retailer": "Xero Shoes",
    "tier": "premium",
    "rating": 4.5,
    "pros": [
      "Wide toe box, zero drop, thin flexible sole — the full barefoot recipe, well made",
      "5,000-mile sole warranty; a forgiving fit for first-timers",
      "Everyday-normal looks; nobody will ask about your toe shoes"
    ],
    "cons": [
      "Several times the price of the budget option for the same geometry",
      "Minimal cushioning is the point — but it's a shock if you skip the slow transition"
    ],
    "bestFor": "Committing to barefoot shoes as your daily driver once the trial month goes well.",
    "verdict": "The sensible premium pick — durable, normal-looking, honestly barefoot.",
    "featured": false
  },
  {
    "id": "maverick-indian-clubs",
    "name": "Wooden Indian Clubs (pair, 1–2 lb)",
    "brand": "Maverick Mace",
    "category": "mobility",
    "price": "$40–$70",
    "priceNote": "Sold direct; no affiliate program — linked for reference.",
    "affiliateUrl": "https://www.maverickmace.com/product/indian-clubs/",
    "retailer": "Maverick Mace",
    "tier": "mid",
    "pros": [
      "Circular swings take the shoulders through ranges no dumbbell visits",
      "So light (1–2 lb) that daily practice is recovery, not training",
      "A 2,000-year-old tool that doubles as the nicest object in the room"
    ],
    "cons": [
      "Real technique to learn — budget a few sessions of following videos",
      "Ceiling fans and clubs are natural enemies"
    ],
    "bestFor": "Desk-rounded shoulders that want gentle, rhythmic, daily unwinding.",
    "verdict": "The most pleasant mobility habit we know. Start with the lightest pair.",
    "featured": false
  },
  {
    "id": "yes4all-steel-mace",
    "name": "Steel Mace (10 lb)",
    "brand": "Yes4All",
    "category": "mobility",
    "price": "$30–$45",
    "priceNote": "Women often start at 7 lb, men at 10 lb — the long lever makes it feel far heavier.",
    "affiliateUrl": "https://www.walmart.com/ip/Yes4All-10lb-Steel-Mace-Bell-Single/973830740",
    "retailer": "Walmart / Amazon",
    "tier": "mid",
    "pros": [
      "The offset load makes 10 lb train shoulders, grip, and core like far more",
      "360s and 10-to-2s build shoulder control through full circles",
      "Nearly indestructible; one purchase, done"
    ],
    "cons": [
      "Requires baseline shoulder mobility you may not have yet — it reinforces range, it doesn't grant it",
      "Easiest tool on this list to swing badly; learn the halo first"
    ],
    "bestFor": "Graduating from clubs and kettlebell halos to bigger circles.",
    "verdict": "The reward tier, not the entry point. Earn it with the basics, then have fun.",
    "featured": false
  }
]
